glmext-1.0.0.dist-info/WHEEL
glmext-1.0.0.dist-info/top_level.txt
glmext-1.0.0.dist-info/METADATA
glmext-1.0.0.dist-info/RECORD
glmext-1.0.0.dist-info/licenses/LICENSE
glmext/loss.py
glmext/glm.py
glmext/__init__.py
glmext/_C/_loss.pyx
glmext/_C/_loss.cpython-39-i386-linux-gnu.so
glmext/_C/_loss.pxd
glmext/_C/__init__.py
