Metadata-Version: 2.4
Name: glmext
Version: 1.0.0
Summary: Generalized Linear Model Extension for Scikit-Learn.
Author: Yunchen Yang
License: MIT License
Classifier: Programming Language :: Python :: 3
Classifier: License :: OSI Approved :: MIT License
Classifier: Operating System :: OS Independent
Classifier: Intended Audience :: Science/Research
Classifier: Intended Audience :: Developers
Classifier: Topic :: Software Development
Classifier: Topic :: Scientific/Engineering
License-File: LICENSE
Requires-Dist: numpy>=1.22.1
Requires-Dist: scikit-learn<=1.8,>=1.4
Provides-Extra: dev
Requires-Dist: jupyter; extra == "dev"
Requires-Dist: pandas; extra == "dev"
Requires-Dist: statsmodels; extra == "dev"
Requires-Dist: matplotlib; extra == "dev"
Dynamic: license-file
